LICENSE
MANIFEST.in
README.rst
ez_setup.py
requirements.txt
setup.py
dotfav/__init__.py
dotfav/__main__.py
dotfav/cmdline.py
dotfav/config.py
dotfav/init.py
dotfav/path.py
dotfav/symlink.py
dotfav/unlink.py
dotfav.egg-info/PKG-INFO
dotfav.egg-info/SOURCES.txt
dotfav.egg-info/dependency_links.txt
dotfav.egg-info/entry_points.txt
dotfav.egg-info/requires.txt
dotfav.egg-info/top_level.txt
features/symlink.feature
features/unlink.feature
features/steps/general_step.py
features/steps/symlink_step.py
features/steps/unlink_setp.py
features/steps/utils.py