Metadata-Version: 1.1
Name: dotfav
Version: 0.1
Summary: dotfiles manager
Home-page: http://github.com/kei10in/dotfav
Author: kei10in
Author-email: UNKNOWN
License: MIT
Keywords: console
Platform: any
Classifier: Development Status :: 4 - Beta
Classifier: Environment :: Console
Classifier: License :: OSI Approved :: MIT License
Classifier: Programming Language :: Python :: 3.3
